{"id":"lmg5200","schema":"integrated_power_stage","display_name":"LMG5200 80-V GaN Half-Bridge Power Stage","vendor":"Texas Instruments","datasheet_url":"https://www.ti.com/lit/ds/symlink/lmg5200.pdf","macro_prefix":"LMG5200","tags":["power_device","gan","half_bridge","integrated_driver","ti"],"parameters":{"part_number":"LMG5200","switch_technology":"GaN FET","configuration":"half_bridge","phase_count":1,"voltage_rating_v":80.0,"current_rating_a":10.0,"rdson_ohm":0.015,"driver_integrated":1,"input_active_level":1,"package":"QFM 8x6"}}
